vacuumms
